[
  {
    "id": 1,
    "name": "national"
  },
  {
    "id": 2,
    "name": "kanto"
  },
  {
    "id": 3,
    "name": "original-johto"
  },
  {
    "id": 4,
    "name": "hoenn"
  },
  {
    "id": 5,
    "name": "original-sinnoh"
  },
  {
    "id": 6,
    "name": "extended-sinnoh"
  },
  {
    "id": 7,
    "name": "updated-johto"
  },
  {
    "id": 8,
    "name": "original-unova"
  },
  {
    "id": 9,
    "name": "updated-unova"
  },
  {
    "id": 11,
    "name": "conquest-gallery"
  },
  {
    "id": 12,
    "name": "kalos-central"
  },
  {
    "id": 13,
    "name": "kalos-coastal"
  },
  {
    "id": 14,
    "name": "kalos-mountain"
  },
  {
    "id": 15,
    "name": "updated-hoenn"
  }
]